mongo_pool/__init__.py
mongo_pool/mongo_pool.py
mongo_pool-0.5.0.dist-info/LICENSE.txt
mongo_pool-0.5.0.dist-info/METADATA
mongo_pool-0.5.0.dist-info/WHEEL
mongo_pool-0.5.0.dist-info/top_level.txt
mongo_pool-0.5.0.dist-info/RECORD
