Metadata-Version: 2.1
Name: mongo-pool
Version: 0.5.0
Summary: The tool that keeps all your mongos in one place
Home-page: http://github.com/ubervu/mongo-pool/
Author: UberVU
Author-email: development@ubervu.com
License: Apache Software License
Platform: any
Classifier: Development Status :: 4 - Beta
Classifier: Environment :: Web Environment
Classifier: Intended Audience :: Developers
Classifier: License :: OSI Approved :: Apache Software License
Classifier: Natural Language :: English
Classifier: Operating System :: OS Independent
Classifier: Programming Language :: Python
Classifier: Topic :: Database
Classifier: Topic :: Software Development :: Libraries :: Python Modules
Requires-Dist: pymongo (>=3.6.1)
Requires-Dist: six (>=1.15.0)
Provides-Extra: testing
Requires-Dist: nose ; extra == 'testing'
Requires-Dist: mock ; extra == 'testing'
